[
	{
		"back_flavor": "TEXT HERE",
		"back_text": "<b>Deck Size</b>: 30.\n<b>Trait Choice</b>: At deck creation, choose 1 trait: <b>Relic</b> or <b>Spirit</b>.\n<b>Deckbuilding Options</b>: Guardian cards ([guardian]) level 0-5, Neutral cards level 0-5, up to 10 other cards of the chosen trait level 0-3.\n<b>Deckbuilding Requirements</b> (do not count toward deck size): Level 0 Kokorowatari(Replica), Koyomi Araragi, Princess Beauty, 1 random basic weakness.\n<b>Additional Requirements:</b> You begin the game with Koyomi Araragi (Half-Vampire) in play. Set aside the level 4 Kokorowatari(Replica) copy as an upgrade.",
		"code": "17701",
		"deck_limit": 1,
		"deck_options": [
			{"faction": ["neutral", "guardian"], "level": {"min":0, "max":5} },
			{"name": "Trait Choice",
				"complex_select": {
					"Relic": {"trait":["relic"], "level":{"min":0, "max":3}, "limit": 10 },
					"Spirit": {"trait":["spirit"], "level":{"min":0, "max":3}, "limit": 10 }
				}
			}
		],
		"deck_requirements": "size:30, card:17706:17707, card:17708, card:17709, random:subtype:basicweakness",
		"double_sided": true,
		"faction_code": "guardian",
		"health": 5,
		"illustrator": "Hong",
		"is_unique": true,
		"name": "Shinobu Oshino",
		"pack_code": "monogatari",
		"position": 1,
		"quantity": 1,
		"sanity": 5,
		"skill_agility": 3,
		"skill_intellect": 2,
		"skill_combat": 5,
		"skill_willpower": 2,
		"subname": "The Former Vampire",
		"text": "Each <b>Ally</b> asset you control gains Linked.\n[reaction] After you defeat an enemy - eat its remains: Heal 1 damage. (Limit once per phase.)\n[elder_sign] effect: +0 If this test results in defeating an enemy, resolve Shinobu Oshino's \"[reaction]\"",
		"traits": "Vampire.",
		"type_code": "investigator"
	},
	{
		"back_flavor": "TEXT HERE",
		"back_text": "<b>Deck Size</b>: 30.\n<b>Trait Choice</b>: At deck creation, choose either <b>Spirit</b>,  <b>Talent</b>, or both traits.\n<b>Deckbuilding Options</b>: Seekers cards ([seeker]) level 0-5, Neutral cards level 0-5, up to 10 other cards of the chosen trait level 0-3(level 0 if you chose both traits, instead), Guardian cards ([guardian]) level 0.\n<b>Deckbuilding Requirements</b> (do not count toward deck size):  Black Hanekawa, Kako, 1 random basic weakness.",
		"code": "17702",
		"deck_limit": 1,
		"deck_options": [
			{"faction":["neutral", "seeker"], "level":{"min":0, "max":5} },
			{"faction":["guardian"], "level":{"min":0, "max":0} },
			{"name": "Trait Choice",
				"complex_select": {
					"Spirit": {"trait":["spirit"], "level":{"min":0, "max":3}, "limit": 10 },
					"Talent": {"trait":["talent"], "level":{"min":0, "max":3}, "limit": 10 },
					"Both": {"trait":["spirit","talent"], "level":{"min":0, "max":0}, "limit": 10 }
				}
			}
		],
		"deck_requirements": "size:30, card:17710, card:17711,  random:subtype:basicweakness",
		"double_sided": true,
		"faction_code": "seeker",
		"health": 8,
		"illustrator": "VOFAN",
		"is_unique": true,
		"name": "Tsubasa Hanekawa",
		"pack_code": "monogatari",
		"position": 2,
		"quantity": 1,
		"sanity": 6,
		"skill_agility": 1,
		"skill_intellect": 5,
		"skill_combat": 1,
		"skill_willpower": 5,
		"subname": "Possessed by a Cat Spirit",
		"text": "[reaction] After 1 or more horror is placed on Tsubasa Hanekawa, take 1 additional horror: Discover 1 clue at your locations.(Limit once per round.)\n[elder_sign] effect: heal 1 horror or ready Black Hanekawa.",
		"traits": "Drifter. Cursed.",
		"type_code": "investigator"
	},
	{
		"back_flavor": "TEXT HERE",
		"back_text": "<b>Deck Size</b>: 30.\n<b>Trait Choice</b>: At deck creation, choose 2 out of 3 traits: <b>Cursed</b>, <b>Trick</b>,  <b>Tactic</b>.\n<b>Deckbuilding Options</b>: Rogue cards ([rogue]) level 0-5, Neutral cards level 0-5, up to 15 other cards of the chosen traits level 0-3.\n<b>Deckbuilding Requirements</b> (do not count toward deck size): Monkey Paw, Valhalla Combo, The Rainy Devil, 1 random basic weakness.",
		"code": "17703",
		"deck_limit": 1,
		"deck_options": [
			{"faction":["rogue", "neutral"], "level":{"min":0, "max":5} },
			{"name": "Trait Choice",
				"complex_select": {
					"Cursed, Tactic": {"trait":["cursed", "tactic"], "level":{"min":0, "max":3}, "limit": 15 },
					"Trick, Tactic": {"trait":["tactic", "trick"], "level":{"min":0, "max":3}, "limit": 15 },
					"Cursed, Trick": {"trait":["cursed", "trick"], "level":{"min":0, "max":3}, "limit": 15 }
				}
			}
		],
		"deck_requirements": "size:30, card:17712, card:17713, card:17714, random:subtype:basicweakness",
		"double_sided": true,
		"faction_code": "rogue",
		"health": 8,
		"illustrator": "VOFAN",
		"is_unique": true,
		"name": "Suruga Kanbaru",
		"pack_code": "monogatari",
		"position": 3,
		"quantity": 1,
		"sanity": 6,
		"skill_agility": 5,
		"skill_intellect": 3,
		"skill_combat": 3,
		"skill_willpower": 1,
		"subname": "The Underclassman",
		"text": "[reaction] After you evade an enemy: Place 1 charge on Monkey Paw (2 charges if you succeeded by 2 or more, instead).(Limit once per round.)\n[elder_sign] effect: +2. Place 1 charge in Monkey Paw.",
		"traits": "Athlete. Cursed.",
		"type_code": "investigator"
	},
	{
		"back_flavor": "TEXT HERE",
		"back_text": "<b>Deck Size</b>: 30.\n<b>Trait Choice</b>: At deck creation, choose either <b>Spell</b> or <b>Ritual</b> to be a primary trait and a secondary trait.\n<b>Deckbuilding Options</b>: Mystic cards ([mystic]) level 0-3, Neutral cards level 0-5, cards of the chosen primary trait level 0-5, up to 10 other cards of the chosen secondary trait level 0-2.\n<b>Deckbuilding Requirements</b> (do not count toward deck size): Unlimited Rulebook (\"I said with a posed look.\"), Unlimited Rulebook (Secession Version), Anatta, 1 random basic weakness.",
		"code": "17704",
		"deck_limit": 1,
		"deck_options": [
			{"faction":["mystic"], "level":{"min":0, "max":3} },
			{"faction":["neutral"], "level":{"min":0, "max":5} },
			{"name": "Trait Choice",
				"complex_select": {
					"Ritual":[
						{"trait":["ritual"], "level":{"min":0, "max":5} },
						{"trait":["spell"], "level":{"min":0, "max":2}, "limit": 10 }
					],
					"Spell":[
						{"trait":["spell"], "level":{"min":0, "max":5} },
						{"trait":["ritual"], "level":{"min":0, "max":2}, "limit": 10 }
					]
				}
			}
		],
		"deck_requirements": "size:30, card:17715, card:17716, card:17717, random:subtype:basicweakness",
		"double_sided": true,
		"faction_code": "mystic",
		"health": 7,
		"illustrator": "VOFAN",
		"is_unique": true,
		"name": "Yotsugi Ononoki",
		"pack_code": "monogatari",
		"position": 4,
		"quantity": 1,
		"sanity": 7,
		"skill_agility": 1,
		"skill_intellect": 2,
		"skill_combat": 1,
		"skill_willpower": 4,
		"subname": "The Living Doll",
		"text": "You get +1 to each of your skills for every two <b>Spell</b> or <b>Ritual</b> assets you control.\n[reaction] After your turn begins: Play a <b>Spell</b> or <b>Ritual</b> asset from your hand, reducing its cost by 2.\n[elder_sign] effect: +1. If you succeed, you may play a <b>Spell</b> or <b>Ritual</b> asset from your hand, at no cost.",
		"traits": "Servitor.",
		"type_code": "investigator"
	},
	{
		"back_flavor": "TEXT HERE",
		"back_text": "<b>Deck Size</b>: 35.\n<b>Trait Choice</b>: At deck creation, either choose <b>Insight</b> or no trait.\n<b>Deckbuilding Options</b>: Survivor cards ([survivor]) level 0-5 (Survivor cards ([survivor]) level 0-2 if you chose <b>Insight</b> instead), Neutral cards level 0-5, up to 10 other <b>Insight</b> cards level 0-5(up to 10 other <b>Insight</b> cards level 0-3 if you chose no trait, instead).\n<b>Deckbuilding Requirements</b> (do not count toward deck size): 2 copies of Limitless Stationery, Weightlessness, High-ranking Cult Member, 1 random basic weakness.",
		"code": "17705",
		"deck_limit": 1,
		"deck_options": [
			{"faction":["neutral"], "level":{"min":0, "max":5} },
			{
				"name": "Trait Choice",
				"complex_select":{
					"Insight":[
						{"faction":["survivor"], "level":{"min":0, "max":2} },
						{"trait":["insight"], "level":{"min":0, "max":5}, "limit": 10 }
					],
					"None":[
						{"faction":["survivor"], "level":{"min":0, "max":5} },
						{"trait":["insight"], "level":{"min":0, "max":3}, "limit": 10 }
					]
				}
			}
		],
		"deck_requirements": "size:35, card:17718, card:17719, card:17721, random:subtype:basicweakness",
		"double_sided": true,
		"faction_code": "survivor",
		"health": 7,
		"illustrator": "VOFAN",
		"is_unique": true,
		"name": "Hitagi Senjougahara",
		"pack_code": "monogatari",
		"position": 5,
		"quantity": 1,
		"sanity": 7,
		"skill_agility": 2,
		"skill_intellect": 4,
		"skill_combat": 2,
		"skill_willpower": 3,
		"subname": "The Graduate",
		"text": "[action] :<b>Draw.</b> Either draw 1 card, or choose and discard 1 card from your hand.\nYou may take an additinal action during your turn, which can only be used to preform the above \"[action]\" ability.\n[elder_sign] effect: +0. Either draw 1 card or choose and discard 1 card.",
		"traits": "Student.",
		"type_code": "investigator"
	},
	{
        "code": "17706",
        "cost": 5,
        "deck_limit": 1,
        "faction_code": "guardian",
        "illustrator": "Drid",
        "is_unique": true,
        "name": "Kokorowatari(Replica)",
        "pack_code": "monogatari",
        "position": 6,
        "quantity": 1,
        "restrictions": "investigator:17701",
        "skill_combat": 1,
        "skill_wild": 1,
        "slot": "Hand x2",
        "subname": "Oddity Slayer",
        "text": "Exceptional. Shinobu Oshino deck only.\n[free] During your turn, exhaust Kokorowatari(Replica): Take 2 damage. Then you may take an additional action, which only can be used to trigger the \"[action]\" ability below.\n[action]: <b>Fight.</b> You get +1 [combat] and deal +1 damage for this attack.",
        "traits": "Item. Weapon. Melee. Relic",
        "type_code": "asset"
    },
	{
        "code": "17707",
        "cost": 6,
        "deck_limit": 1,
        "faction_code": "guardian",
        "illustrator": "Drid",
        "is_unique": true,
        "name": "Kokorowatari(Replica)",
        "pack_code": "monogatari",
        "position": 7,
        "quantity": 1,
        "restrictions": "investigator:17701",
        "skill_combat": 2,
        "skill_wild": 1,
        "slot": "Hand x2",
        "subname": "Oddity Slayer",
        "text": "Exceptional. Shinobu Oshino deck only.\n[free] During your turn, exhaust Kokorowatari(Replica): Take 2 damage. Then you may take an additional action, which only can be used to trigger the \"[action]\" ability below.\n[action]: <b>Fight.</b> You get +2 [combat] and deal +2 damage for this attack.",
        "traits": "Item. Weapon. Melee. Relic",
        "type_code": "asset",
		"xp": 8
    },	
	{
        "code": "17708",
        "cost": null,
        "deck_limit": 1,
        "faction_code": "guardian",
		"health": 3,
        "illustrator": "",
        "is_unique": true,
        "name": "Koyomi Araragi",
        "pack_code": "monogatari",
        "position": 8,
        "quantity": 1,
        "restrictions": "investigator:17701",
		"sanity": null,
        "subname": "Half Vampire",
        "text": "Permanent. Shinobu Oshino deck only.\n[reaction] After you heal 1 or more damage from Koyomi Araragi, exhaust him: Draw 1 card.\n <b>Forced</b> - When Koyomi Araragi is defeated: Removed all damage from him and flip him.\n <b>Backside</b>\nPermanent.(You cannot assign damage to Koyomi Araragi.)\nYou get -3 [combat].\n[action][action]: Flip Koyomi Araragi. Then place 2 damage on him.",
        "traits": "Ally. Vampire",
        "type_code": "asset"
    },
	{
        "code": "17709",
        "deck_limit": 1,
        "faction_code": "neutral",
        "flavor": "",
        "illustrator": "Isana Kagami",
        "name": "Princess Beauty",
        "pack_code": "monogatari",
        "position": 9,
        "quantity": 1,
		"restrictions": "investigator:17701",
        "subtype_code": "weakness",
        "text": "<b>Revelation</b> - Remove all damage from Koyomi Araragi(Half Vampire) and flip him. If Koyomi Araragi is already flipped to his (Half-dead) side, take 1 horror and shuffle Princess Beauty back into your deck.",
        "traits": "Madness.",
        "type_code": "treachery"
    },
	{
        "code": "17710",
        "cost": null,
        "deck_limit": 1,
        "faction_code": "seeker",
        "illustrator": "VOFAN",
        "is_unique": true,
        "name": "Black Hanekawa",
        "pack_code": "monogatari",
        "position": 10,
        "quantity": 1,
        "restrictions": "investigator:17702",
        "subname": "Sawarineko",
        "text": "Permanent. Tsubasa Hanekawa deck only.\n While Tsubasa Hanekawa has 3 or fewer remaining sanity, Black Hanekawa gains: \"Switch the base values of your [intellect] and [combat]. Switch the base values of your [willpower] and [agility].\n[reaction] After you deal damage to an enemy by an attack, exhaust Black Hanekawa: <b>Energy Drain.</b> Either deal 1 additinal damage or heal 1 horror.",
        "traits": "Cat. Conspirator",
        "type_code": "asset"
    },
	{
        "code": "17711",
		"cost": 2,
        "deck_limit": 1,
        "faction_code": "neutral",
        "flavor": "",
        "illustrator": "VOFAN",
        "name": "Kako",
        "pack_code": "monogatari",
        "position": 11,
        "quantity": 1,
		"restrictions": "investigator:17702",
        "subtype_code": "weakness",
        "text": "While Kako is in your hand, you cannot trigger [reaction] abilities except for the ability printed below.\nShuffle Kako into your deck.\n[reaction] When you would play Kako, if Black Hanekawa is in your play area: Cancel all its effects and discard Kako.",
        "traits": "Madness.",
        "type_code": "event"
    },
	{
        "code": "17712",
        "cost": null,
        "deck_limit": 1,
        "faction_code": "rogue",
        "illustrator": "VOFAN",
        "is_unique": true,
        "name": "Monkey Paw",
        "pack_code": "monogatari",
        "position": 12,
        "quantity": 1,
        "restrictions": "investigator:17703",
        "subname": "Granting \"wishes\"",
        "text": "Premanent. Suruga Kanbaru deck only. Uses (0 charges). Limit 6 charges on Monkey Paw.\n[reaction] When your turn begins, spend up to 6 charges: For every 2 charges spent as part of this ability's cost; you may take an additional action this turn.",
        "traits": "Cursed. Relic.",
        "type_code": "asset"
    },
	{
        "code": "17713",
        "cost": 2,
        "deck_limit": 1,
        "faction_code": "rogue",
        "flavor": "",
        "illustrator": "VOFAN",
        "name": "Valhalla Combo",
        "pack_code": "monogatari",
        "position": 13,
        "quantity": 1,
        "restrictions": "investigator:17703",
        "skill_agility": 2,
        "skill_wild": 2,
        "text": "Suruga Kanbaru deck only.\nPlay only during your turn.\n<b>Engage.Evade.</b> Choose a revealed location. Move to that location if you are not already there. Engage all enemies at that location. One at a time, attempt to evade each enemy that you have engaged. For each enemy you have successsfully evaded, pace 1 charge on Monkey Paw.",
        "traits": "Trick.",
        "type_code": "event"
    },
	{
        "code": "17714",
        "deck_limit": 1,
        "faction_code": "neutral",
        "flavor": "",
        "illustrator": "Hong",
        "name": "The Rainy Devil",
        "pack_code": "monogatari",
        "position": 14,
        "quantity": 1,
		"restrictions": "investigator:17703",
        "subtype_code": "weakness",
        "text": "If there are 1 or fewer charges on Monkey Pawm, shuffle The Rainy Devil back into your deck. Otherwise for every 2 charges on Monkey Paw, you must either deal 2 damage to another investigator at your loctation or take 1 horror.",
        "traits": "Curse.",
        "type_code": "treachery"
    },
	{
        "code": "17715",
        "cost": 4,
        "deck_limit": 1,
        "faction_code": "mystic",
        "illustrator": "Stagain",
        "name": "Unlimited Rulebook",
        "pack_code": "monogatari",
        "position": 15,
        "quantity": 1,
        "restrictions": "investigator:17704",
		"skill_will": 1,
        "skill_combat": 1,
        "skill_wild": 1,
        "slot": "Arcane",
        "subname": "\"I said with a posed look.\"",
        "text": "Yotsugi Ononoki deck only.\n[action] Return Unlimited Rulebook to your hand and take 1 horror: Reveal 8 tokens from the chaos bag. For each token with an odd modifier you reveal, deal 1 damage to an enemy at your location. This action does not provoke attacks of opportunity.",
        "traits": "Spell. Ritual.",
        "type_code": "asset"
    },
	{
        "code": "17716",
        "cost": 4,
        "deck_limit": 1,
        "faction_code": "mystic",
        "illustrator": "VOFAN",
        "name": "Unlimited Rulebook",
        "pack_code": "monogatari",
        "position": 16,
        "quantity": 1,
        "restrictions": "investigator:17704",
		"skill_will": 1,
        "skill_agility": 1,
        "skill_wild": 1,
        "slot": "Arcane",
        "subname": "Secession Version",
        "text": "Yotsugi Ononoki deck only.\n[action] Return Unlimited Rulebook to your hand and take 1 damage: Disengage from each enemy engaged with you and move to any revealed location. You may move another investigator at this location from this ability as well. If you do, that investigator takes 1 damage. This action does not provoke attacks of opportunity.",
        "traits": "Spell. Ritual.",
        "type_code": "asset"
    },
	{
        "code": "17717",
        "deck_limit": 1,
        "faction_code": "neutral",
        "flavor": "",
        "illustrator": "VOFAN",
        "name": "Anatta",
        "pack_code": "monogatari",
        "position": 17,
        "quantity": 1,
		"restrictions": "investigator:17704",
        "subtype_code": "weakness",
        "text": "<b>Revelation</b> - Name either <b>Spell</b> or <b>Ritual</b>. Discard each asset you control that has the named trait. If no assets are discarded by this effect, take 1 horror and shufffle Anatta back into your deck.",
        "traits": "Flaw.",
        "type_code": "treachery"
    },
	{
        "code": "17718",
        "cost": 3,
        "deck_limit": 1,
        "faction_code": "survivor",
        "illustrator": "MadYY",
        "name": "Weightlessness",
        "pack_code": "monogatari",
        "position": 18,
        "quantity": 1,
        "restrictions": "investigator:17705",
		"skill_intellect": 1,
        "skill_combat": 1,
        "skill_wild": 1,
        "text": "Hitagi Senjougahara deck only.\n[reaction] After you discard 1 or more cards from your hand, exhaust Weightlessness: Draw 1 card or gain 1 resource.",
        "traits": "Talent.",
        "type_code": "asset"
    },
	{
        "code": "17719",
        "cost": 1,
        "deck_limit": 2,
        "faction_code": "survivor",
        "flavor": "",
        "illustrator": "Reniirean",
        "name": "Limitless Stationery",
        "pack_code": "monogatari",
        "position": 19,
        "quantity": 1,
        "restrictions": "investigator:17705",
        "text": "Hitagi Senjougahara deck only.\nLimitless Stationery annot be played or committed from your hand.\nDiscover 1 clue at your location.\n[reaction] After you discard Limitless Stationery from your hand during your turn: Play it. (Limit 1 <b>Introspection</b> ability per discard.)",
        "traits": "Introspection.",
        "type_code": "event"
    },
	{
        "code": "17721",
        "deck_limit": 1,
        "enemy_damage": 1,
        "enemy_evade": 3,
        "enemy_fight": 3,
        "enemy_horror": 1,
        "faction_code": "neutral",
        "flavor": "",
        "health": 3,
        "illustrator": "Damien Mammoliti",
        "name": "High-ranking Cult Member",
        "pack_code": "monogatari",
        "position": 21,
        "quantity": 1,
		"restrictions": "investigator:17705",
        "subtype_code": "weakness",
        "text": "<b>Prey<b/> - Hitagi Senjougahara only.\nAmbush.Hunter.\n<b>Forced<b/> - After you draw 1 or more cards or discard 1 or more cards from your hand during your turn while High-ranking Cult Member is engaged with you: It attacks you.",
        "traits": "Humanoid. Cultist.",
        "type_code": "enemy"
    }
]