[
    {
        "code": "03106",
        "cost": 1,
        "deck_limit": 2,
        "faction_code": "guardian",
        "illustrator": "Cynthia Sheppard",
        "name": "Heroic Rescue",
        "pack_code": "eotp",
        "position": 106,
        "quantity": 2,
        "skill_willpower": 1,
        "skill_combat": 1,
        "text": "Fast. Play when a non-[[Elite]] enemy would attack another investigator at your location.\nEngage that enemy and resolve its attack against you instead. Then, deal it 1 damage.",
        "traits": "Spirit. Tactic.",
        "type_code": "event",
        "xp": 0
    },
    {
        "code": "03107",
        "cost": 1,
        "deck_limit": 2,
        "faction_code": "guardian",
        "illustrator": "RJ Palmer",
        "name": "Combat Training",
        "pack_code": "eotp",
        "position": 107,
        "quantity": 2,
        "sanity": 1,
        "skill_combat": 1,
        "skill_agility": 1,
        "text": "Fast. Limit 1 [[Composure]] in play.\nNon-direct horror must be assigned to Combat Training before it can be assigned to your investigator card.\n[free] Spend 1 resource: You get +1 [combat] for this skill test.\n[free] Spend 1 resource: You get +1 [agility] for this skill test.",
        "traits": "Talent. Composure.",
        "type_code": "asset",
        "xp": 1
    },
    {
        "code": "03108",
        "cost": 1,
        "deck_limit": 2,
        "faction_code": "seeker",
        "illustrator": "Stephen Somers",
        "name": "Anatomical Diagrams",
        "pack_code": "eotp",
        "position": 108,
        "quantity": 2,
        "skill_willpower": 1,
        "skill_combat": 1,
        "text": "Fast. Play during any investigator's turn. Play only if you have 5 or more remaining sanity.\nChoose a non-[[Elite]] enemy at your location. Until the end of the active investigator's turn, that enemy gets -2 fight and -2 evade.",
        "traits": "Insight.",
        "flavor": "They are just animals like any other. Or so we thought.",
        "type_code": "event",
        "xp": 0
    },
    {
        "code": "03109",
        "cost": 1,
        "deck_limit": 2,
        "faction_code": "seeker",
        "illustrator": "Mark Molnar",
        "name": "Scientific Theory",
        "pack_code": "eotp",
        "position": 109,
        "quantity": 2,
        "sanity": 1,
        "skill_intellect": 1,
        "skill_combat": 1,
        "text": "Fast. Limit 1 [[Composure]] in play.\nNon-direct horror must be assigned to Scientific Theory before it can be assigned to your investigator card.\n[free] Spend 1 resource: You get +1 [intellect] for this skill test.\n[free] Spend 1 resource: You get +1 [combat] for this skill test.",
        "traits": "Talent. Composure.",
        "type_code": "asset",
        "xp": 1
    },
    {
        "code": "03110",
        "cost": 2,
        "deck_limit": 2,
        "faction_code": "rogue",
        "flavor": "Up close and personal:\njust the way Naomi liked it.",
        "illustrator": "John Pacer",
        "name": "Knuckleduster",
        "pack_code": "eotp",
        "position": 110,
        "quantity": 2,
        "skill_combat": 1,
        "slot": "Hand",
        "text": "[action]: <b>Fight.</b> This attack deals +1 damage. The attacked enemy gains retaliate for this attack.",
        "traits": "Item. Weapon. Melee. Illicit.",
        "type_code": "asset",
        "xp": 0
    },
    {
        "code": "03111",
        "cost": 1,
        "deck_limit": 2,
        "faction_code": "rogue",
        "illustrator": "Jeff Lee Johnson",
        "name": "Moxie",
        "pack_code": "eotp",
        "position": 111,
        "quantity": 2,
        "sanity": 1,
        "skill_willpower": 1,
        "skill_agility": 1,
        "text": "Fast. Limit 1 [[Composure]] in play.\nNon-direct horror must be assigned to Moxie before it can be assigned to your investigator card.\n[free] Spend 1 resource: You get +1 [willpower] for this skill test.\n[free] Spend 1 resource: You get +1 [agility] for this skill test.",
        "traits": "Talent. Composure.",
        "type_code": "asset",
        "xp": 1
    },
    {
        "code": "03112",
        "cost": 2,
        "deck_limit": 2,
        "faction_code": "mystic",
        "illustrator": "Alexandre Dainche",
        "is_unique": true,
        "name": "David Renfield",
        "subname": "Esteemed Eschatologist",
        "pack_code": "eotp",
        "position": 112,
        "quantity": 2,
        "health": 2,
        "sanity": 1,
        "skill_intellect": 1,
        "text": "While David Renfield has at least 1 doom on him, you get +1 [willpower].\n[fast] Exhaust David Renfield: You may place 1 doom on David Renfield. Gain 1 resource for each doom on David Renfield.",
        "traits": "Ally. Patron.",
        "type_code": "asset",
        "slot": "Ally",
        "xp": 0
    },
    {
        "code": "03113",
        "cost": 1,
        "deck_limit": 2,
        "faction_code": "mystic",
        "illustrator": "Ilich Henriquez",
        "name": "Grounded",
        "pack_code": "eotp",
        "position": 113,
        "quantity": 2,
        "sanity": 1,
        "skill_willpower": 1,
        "text": "Fast. Limit 1 [[Composure]] in play.\nNon-direct horror must be assigned to Grounded before it can be assigned to your investigator card.\n[free] During a skill test on a [[Spell]] card, spend 1 resource: You get +1 skill value for this test.",
        "traits": "Talent. Composure.",
        "type_code": "asset",
        "xp": 1
    },
    {
        "code": "03114",
        "cost": 0,
        "deck_limit": 2,
        "faction_code": "survivor",
        "illustrator": "Robert Laskey",
        "name": "Cherished Keepsake",
        "pack_code": "eotp",
        "position": 114,
        "quantity": 2,
        "sanity": 2,
        "skill_willpower": 1,
        "traits": "Item. Charm.",
        "flavor": "Mr. Pawterson always told Wendy things would turn out okay. But then again, Mr. Pawterson was a teddy bear, and he didn't know any better.",
        "type_code": "asset",
        "slot": "Accessory",
        "xp": 0
    },
    {
        "code": "03115",
        "cost": 1,
        "deck_limit": 2,
        "faction_code": "survivor",
        "illustrator": "Dani Hartel",
        "name": "Plucky",
        "pack_code": "eotp",
        "position": 115,
        "quantity": 2,
        "sanity": 1,
        "skill_intellect": 1,
        "skill_willpower": 1,
        "text": "Fast. Limit 1 [[Composure]] in play.\nNon-direct horror must be assigned to Plucky before it can be assigned to your investigator card.\n[free] Spend 1 resource: You get +1 [willpower] for this skill test.\n[free] Spend 1 resource: You get +1 [intellect] for this skill test.",
        "traits": "Talent. Composure.",
        "type_code": "asset",
        "xp": 1
    },
    {
        "code": "03116",
        "deck_limit": 2,
        "faction_code": "neutral",
        "illustrator": "Melissa Findley",
        "name": "Say Your Prayers",
        "pack_code": "eotp",
        "position": 116,
        "quantity": 2,
        "skill_willpower": 4,
        "text": "Max 1 committed per skill test.\nCommit to a skill test only if you have 3 or fewer remaining sanity.",
        "traits": "Desperate.",
        "type_code": "skill",
        "xp": 0
    },
    {
        "code": "03117",
        "deck_limit": 2,
        "faction_code": "neutral",
        "illustrator": "Cristina Vela",
        "name": "Desperate Search",
        "pack_code": "eotp",
        "position": 117,
        "quantity": 2,
        "skill_intellect": 4,
        "text": "Max 1 committed per skill test.\nCommit to a skill test only if you have 3 or fewer remaining sanity.",
        "traits": "Desperate.",
        "type_code": "skill",
        "xp": 0
    },
    {
        "code": "03118",
        "deck_limit": 2,
        "faction_code": "neutral",
        "illustrator": "Nicholas Stohlman",
        "name": "Reckless Assault",
        "pack_code": "eotp",
        "position": 118,
        "quantity": 2,
        "skill_combat": 4,
        "text": "Max 1 committed per skill test.\nCommit to a skill test only if you have 3 or fewer remaining sanity.",
        "traits": "Desperate.",
        "type_code": "skill",
        "xp": 0
    },
    {
        "code": "03119",
        "deck_limit": 2,
        "faction_code": "neutral",
        "illustrator": "Nicholas Elias",
        "name": "Run For Your Life",
        "pack_code": "eotp",
        "position": 119,
        "quantity": 2,
        "skill_agility": 4,
        "text": "Max 1 committed per skill test.\nCommit to a skill test only if you have 3 or fewer remaining sanity.",
        "traits": "Desperate.",
        "type_code": "skill",
        "xp": 0
    }
]
