[
    {
        "back_text": "Hard / Expert\n[skull]: -X. X is 1 more than the number of keys the investigators control.\n[cultist]: -3. If this is an attack or evasion attempt against a [[Deep One]] enemy, it engages you. (If it is already engaged with you, it disengages first, then re-engages you.)\n[tablet]: -4. If you are not in a vehicle, take 1 damage.\n[elder_thing]: -5. If your location has a key on it, take 1 horror.",
        "code": "07163",
        "double_sided": true,
        "encounter_code": "devil_reef",
        "encounter_position": 1,
        "faction_code": "mythos",
        "name": "Devil Reef",
        "pack_code": "def",
        "position": 163,
        "quantity": 1,
        "text": "Easy / Standard\n[skull]: -X. X is the number of keys the investigators control.\n[cultist]: -2. If you fail and this is an attack or evasion attempt against a [[Deep One]] enemy, it engages you. (If it is already engaged with you, it disengages first, then re-engages you.)\n[tablet]: -3. If you fail and you are not in a vehicle, take 1 damage.\n[elder_thing]: -4. If you fail and your location has a key on it, take 1 horror.",
        "type_code": "scenario"
    },
    {
        "back_link": "07164b",
        "code": "07164",
        "doom": 9,
        "encounter_code": "devil_reef",
        "encounter_position": 2,
        "faction_code": "mythos",
        "flavor": "The sailors along the docks of Innsmouth eye you with suspicion as you depart. The lighthouse beacon at the top of the nearby cliffside provides your only illumination as you head deeper into the fog.",
        "illustrator": "Mark Molnar",
        "name": "Secrets of the Sea (v. I)",
        "pack_code": "def",
        "position": 164,
        "quantity": 1,
        "stage": 1,
        "text": "As an additional cost for you to move from one [[Ocean]] location to another while not in a vehicle, you must spend 2 actions.\n<b>Forced</b> - When your turn begins, if you are at a fully flooded location, you struggle for air: When your turn ends, if you did not enter an unflooded location, partially flooded location, or a vehicle during your turn, take 5 direct damage.",
        "type_code": "agenda"
    },
    {
        "code": "07164b",
        "encounter_code": "devil_reef",
        "encounter_position": 2,
        "enemy_damage": 2,
        "enemy_evade": 3,
        "enemy_fight": 3,
        "enemy_horror": 2,
        "faction_code": "mythos",
        "flavor": "\"It's got us in its grip! It ain't goin' nowhere. Now's your chance!\"",
        "health": 6,
        "hidden": true,
        "illustrator": "Mark Winters",
        "is_unique": true,
        "name": "The Terror of Devil Reef",
        "pack_code": "def",
        "position": 164,
        "quantity": 1,
        "subname": "Grasping Abomination",
        "text": "<b>Spawn</b> - Fishing Vessel's location.\nHunter. Massive. Retaliate.\nThe Terror of Devil Reef cannot enter [[Cave]] locations.\nThe Terror of Devil Reef gets +3 [per_investigator] health.",
        "traits": "Monster. Elite.",
        "type_code": "enemy",
        "victory": 1
    },
    {
        "back_link": "07165b",
        "code": "07165",
        "doom": 9,
        "encounter_code": "devil_reef",
        "encounter_position": 3,
        "faction_code": "mythos",
        "flavor": "The sailors along the docks of Innsmouth eye you with suspicion as you depart. The lighthouse beacon at the top of the nearby cliffside provides your only illumination as you head deeper into the fog.",
        "illustrator": "Mark Molnar",
        "name": "Secrets of the Sea (v. II)",
        "pack_code": "def",
        "position": 165,
        "quantity": 1,
        "stage": 1,
        "text": "As an additional cost for you to move from one [[Ocean]] location to another while not in a vehicle, you must spend 2 actions.\n<b>Forced</b> - When your turn begins, if you are at a fully flooded location, you struggle for air: When your turn ends, if you did not enter an unflooded location, partially flooded location, or a vehicle during your turn, take 5 direct damage.",
        "type_code": "agenda"
    },
    {
        "code": "07165b",
        "encounter_code": "devil_reef",
        "encounter_position": 3,
        "enemy_damage": 2,
        "enemy_evade": 3,
        "enemy_fight": 3,
        "enemy_horror": 2,
        "faction_code": "mythos",
        "health": 6,
        "hidden": true,
        "illustrator": "Mark Winters",
        "is_unique": true,
        "name": "The Terror of Devil Reef",
        "pack_code": "def",
        "position": 165,
        "quantity": 1,
        "subname": "Writhing in the Deep",
        "text": "<b>Spawn</b> - Fishing Vessel's location.\nHunter. Massive. Retaliate.\nThe Terror of Devil Reef cannot enter [[Cave]] locations.\n<b>Forced</b> - When The Terror of Devil Reef would be defeated: Instead, remove all damage from it and exhaust it. It cannot ready for the remainder of the round <i>(including the upkeep phase)</i>.",
        "traits": "Monster. Elite.",
        "type_code": "enemy"
    },
    {
        "back_flavor": "\"We've gotta pull back!\" Mr. Moore shouts over the roar of the waves. \"The sea's too rough, and the tide's gettin' worse by the minute! Stay out here any longer an' we'll capsize fer sure!\"\nYou protest, but the captain is right. The weather has gotten so bad Mr. Moore can barely control the ship. Worse yet, in just a matter of hours the tide has begun to swallow the coastal islands, leaving little for you to investigate. You nod to the captain, frustrated. This will have to do for now.",
        "back_name": "Triumph of the Waves",
        "back_text": "Record in your Campaign Log <i>the tide has grown stronger</i>.\n<b>(→R1)</b>",
        "code": "07166",
        "doom": 9,
        "double_sided": true,
        "encounter_code": "devil_reef",
        "encounter_position": 4,
        "faction_code": "mythos",
        "flavor": "Now you know why none dare venture near the black reefs. It's not just the strange sightings on the islands - there is something far older and more horrifying that dwells under the waves...",
        "illustrator": "Mark Molnar",
        "name": "The Devil of the Depths",
        "pack_code": "def",
        "position": 166,
        "quantity": 1,
        "stage": 2,
        "text": "As an additional cost for you to move from one [[Ocean]] location to another while not in a vehicle, you must spend 2 actions.\n<b>Forced</b> - When your turn begins, if you are at a fully flooded location, you struggle for air: When your turn ends, if you did not enter an unflooded location, partially flooded location, or a vehicle during your turn, take 5 direct damage.",
        "type_code": "agenda"
    },
    {
        "back_flavor": "Confident that you've found enough evidence of the Order's activities, you head back to the coast. You'd much rather continue your investigation on dry land.",
        "back_name": "Secrets Uncovered",
        "back_text": "<b>(→R1)</b>",
        "clues": null,
        "code": "07167",
        "double_sided": true,
        "encounter_code": "devil_reef",
        "encounter_position": 5,
        "faction_code": "mythos",
        "flavor": "Somewhere in these accursed reefs, the Esoteric Order of Dagon is hiding something big... but what?",
        "illustrator": "Alan Dillingham",
        "name": "Reef of Mysteries",
        "pack_code": "def",
        "position": 167,
        "quantity": 1,
        "stage": 1,
        "text": "Keys can only be claimed from [[Y'ha-nthlei]] locations using the [free] ability on those locations.\n<b>Objective</b> - Find and claim as many of the following keys as you can from [[Y'ha-nthlei]] locations (purple, white, and black). If you control all 3 of these keys, advance.",
        "type_code": "act"
    },
    {
        "back_text": "Churning Waters enters play fully flooded <i>(even while it is unrevealed)</i>.",
        "back_flavor": "\"And far out at sea, despite a high tide, I glimpsed a long, black line scarcely rising above the water yet carrying a suggestion of odd latent malignancy.\" - H. P. Lovecraft, <u>The Shadow over Innsmouth</u>",
        "clues": 0,
        "code": "07168",
        "double_sided": true,
        "encounter_code": "devil_reef",
        "encounter_position": 6,
        "faction_code": "mythos",
        "illustrator": "Adam Lane",
        "name": "Churning Waters",
        "pack_code": "def",
        "position": 168,
        "quantity": 1,
        "shroud": 6,
        "text": "[action] If you are in the Fishing Vessel: <b>Resign.</b> Each investigator in the Fishing Vessel resigns. Remove Fishing Vessel from the game. Each resigning investigator places each of their purple, black, or white keys on the current act. All other investigators are left to fend for themselves.",
        "traits": "Ocean.",
        "type_code": "location"
    },
    {
        "back_flavor": "\"...as I glimpsed it I could not help thinking of all the hideous legends I had heard in the last twenty-four hours - legends which portrayed this ragged rock as a veritable gateway to realms of unfathomed horror and inconceivable abnormality.\" - H. P. Lovecraft, <u>The Shadow over Innsmouth</u>",
        "back_illustrator": "Jorge Ramos Márquez",
        "back_name": "Devil Reef",
        "clues": 0,
        "code": "07169",
        "double_sided": true,
        "encounter_code": "devil_reef",
        "encounter_position": 7,
        "faction_code": "mythos",
        "illustrator": "Ryan Barger",
        "name": "Lonely Isle",
        "pack_code": "def",
        "position": 169,
        "quantity": 1,
        "shroud": 5,
        "text": "<b>Forced</b> - After Lonely Isle is revealed: Put 2 random set-aside Tidal Tunnels into play, each adjacent to Lonely Isle (but not to one another).",
        "traits": "Ocean. Island.",
        "type_code": "location"
    },
    {
        "back_flavor": "\"...as I glimpsed it I could not help thinking of all the hideous legends I had heard in the last twenty-four hours - legends which portrayed this ragged rock as a veritable gateway to realms of unfathomed horror and inconceivable abnormality.\" - H. P. Lovecraft, <u>The Shadow over Innsmouth</u>",
        "back_illustrator": "Jorge Ramos Márquez",
        "back_name": "Devil Reef",
        "clues": 0,
        "code": "07170",
        "double_sided": true,
        "encounter_code": "devil_reef",
        "encounter_position": 8,
        "faction_code": "mythos",
        "illustrator": "Carlos Palma Cruchaga",
        "name": "Hidden Cove",
        "pack_code": "def",
        "position": 170,
        "quantity": 1,
        "shroud": 3,
        "text": "<b>Forced</b> - After you reveal Hidden Cove: Put 1 set-aside Tidal Tunnel into play adjacent to Hidden Cove, then put 1 set-aside Unfathomable Depths into play adjacent to that Tidal Tunnel.",
        "traits": "Ocean. Island.",
        "type_code": "location"
    },
    {
        "back_flavor": "\"...as I glimpsed it I could not help thinking of all the hideous legends I had heard in the last twenty-four hours - legends which portrayed this ragged rock as a veritable gateway to realms of unfathomed horror and inconceivable abnormality.\"\n- H. P. Lovecraft, <u>The Shadow over Innsmouth</u>",
        "back_illustrator": "Jorge Ramos Márquez",
        "back_name": "Devil Reef",
        "clues": 0,
        "code": "07171",
        "double_sided": true,
        "encounter_code": "devil_reef",
        "encounter_position": 9,
        "faction_code": "mythos",
        "illustrator": "Dual Brush Studios",
        "name": "Waveworn Island",
        "pack_code": "def",
        "position": 171,
        "quantity": 1,
        "shroud": 4,
        "text": "<b>Forced</b> - After you reveal Waveworn Island: Increase its flood level. Put 1 random set-aside Unfathomable Depths and 2 random set-aside Tidal Tunnels into play, each adjacent to Waveworn Island (but not to one another).",
        "traits": "Ocean. Island.",
        "type_code": "location"
    },
    {
        "back_flavor": "\"...as I glimpsed it I could not help thinking of all the hideous legends I had heard in the last twenty-four hours - legends which portrayed this ragged rock as a veritable gateway to realms of unfathomed horror and inconceivable abnormality.\"\n- H. P. Lovecraft, <u>The Shadow over Innsmouth</u>",
        "back_illustrator": "Jorge Ramos Márquez",
        "back_name": "Devil Reef",
        "clues": 0,
        "code": "07172",
        "double_sided": true,
        "encounter_code": "devil_reef",
        "encounter_position": 10,
        "faction_code": "mythos",
        "illustrator": "David Frasheski",
        "name": "Salt Marshes",
        "pack_code": "def",
        "position": 172,
        "quantity": 1,
        "shroud": 4,
        "text": "[action] If you control the purple key: Look at the revealed side of any Tidal Tunnels or Unfathomable Depths location in play. (Group limit once per game.)\n<b>Forced</b> - After you reveal Salt Marshes: Increase its flood level. Put 1 random set-aside Tidal Tunnel into play adjacent to Salt Marshes.",
        "traits": "Ocean. Island.",
        "type_code": "location"
    },
    {
        "back_flavor": "\"...as I glimpsed it I could not help thinking of all the hideous legends I had heard in the last twenty-four hours - legends which portrayed this ragged rock as a veritable gateway to realms of unfathomed horror and inconceivable abnormality.\"\n- H. P. Lovecraft, <u>The Shadow over Innsmouth</u>",
        "back_illustrator": "Jorge Ramos Márquez",
        "back_name": "Devil Reef",
        "clues": 0,
        "code": "07173",
        "double_sided": true,
        "encounter_code": "devil_reef",
        "encounter_position": 11,
        "faction_code": "mythos",
        "illustrator": "Emilio Rodriguez",
        "name": "Black Reef",
        "pack_code": "def",
        "position": 173,
        "quantity": 1,
        "shroud": 2,
        "text": "<b>Forced</b> - After you reveal Black Reef: Increase its flood level. Put 2 random set-aside Tidal Tunnels into play, each adjacent to Black Reef (but not to one another). Then, put 1 random set-aside Unfathomable Depths into play adjacent to both of those Tidal Tunnels.",
        "traits": "Ocean. Island.",
        "type_code": "location"
    },
    {
        "back_flavor": "The air is frigid here, and there is no sound but the faint plinking of water dripping onto the rough stone ground. You shudder and proceed onward...",
        "back_illustrator": "Patrick McEvoy",
        "back_name": "Tidal Tunnel",
        "clues": 1,
        "code": "07174a",
        "double_sided": true,
        "encounter_code": "devil_reef",
        "encounter_position": 12,
        "faction_code": "mythos",
        "illustrator": "Álvaro Calvo Escudero",
        "name": "Bootlegger's Hideaway",
        "pack_code": "def",
        "position": 174,
        "quantity": 1,
        "shroud": 4,
        "text": "<b>Forced</b> - After Bootlegger's Hideaway is revealed: Randomly choose 1 of the set-aside facedown keys and place it on Bootlegger's Hideaway without looking at it.\n[action] If you control the white key: Draw 3 cards. (Group limit once per game.)",
        "traits": "Cave.",
        "type_code": "location",
        "victory": 1
    },
    {
        "back_flavor": "The air is frigid here, and there is no sound but the faint plinking of water dripping onto the rough stone ground. You shudder and proceed onward...",
        "back_illustrator": "Patrick McEvoy",
        "back_name": "Tidal Tunnel",
        "clues": 1,
        "code": "07174b",
        "double_sided": true,
        "encounter_code": "devil_reef",
        "encounter_position": 13,
        "faction_code": "mythos",
        "illustrator": "Álvaro Calvo Escudero",
        "name": "Bootlegger's Hideaway",
        "pack_code": "def",
        "position": 174,
        "quantity": 1,
        "shroud": 4,
        "text": "<b>Forced</b> - After Bootlegger's Hideaway is revealed: Randomly choose 1 of the set-aside facedown keys and place it on Bootlegger's Hideaway without looking at it.\n[action] If you control the black key: Gain 5 resources. (Group limit once per game.)",
        "traits": "Cave.",
        "type_code": "location",
        "victory": 1
    },
    {
        "back_flavor": "\"They had all kinds o' cities on the sea-bottom, an' this island was heaved up from thar.\"\n- H. P. Lovecraft, <u>The Shadow over Innsmouth</u>",
        "back_illustrator": "Frej Agelii",
        "back_name": "Unfathomable Depths",
        "clues": 1,
        "code": "07175a",
        "double_sided": true,
        "encounter_code": "devil_reef",
        "encounter_position": 14,
        "faction_code": "mythos",
        "illustrator": "Andrew Olson",
        "name": "Deep One Grotto",
        "pack_code": "def",
        "position": 175,
        "quantity": 1,
        "shroud": 4,
        "text": "<b>Forced</b> - After this location is revealed: Increase its flood level. Place the set-aside purple key on it.\n[free] If investigators at this location control both the red key and the blue key and spend 2 [per_investigator] clues, as a group: Take control of the purple key and read <b>Flashback IX</b> in the Campaign Guide.",
        "traits": "Cave. Y'ha-nthlei.",
        "type_code": "location"
    },
    {
        "back_flavor": "\"They had all kinds o' cities on the sea-bottom, an' this island was heaved up from thar.\" - H. P. Lovecraft, <u>The Shadow over Innsmouth</u>",
        "back_illustrator": "Frej Agelii",
        "back_name": "Unfathomable Depths",
        "clues": 2,
        "code": "07175b",
        "double_sided": true,
        "encounter_code": "devil_reef",
        "encounter_position": 15,
        "faction_code": "mythos",
        "illustrator": "Andrew Olson",
        "name": "Deep One Grotto",
        "pack_code": "def",
        "position": 175,
        "quantity": 1,
        "shroud": 2,
        "text": "<b>Forced</b> - After this location is revealed: Increase its flood level. Place the set-aside purple key on it.\n[free] If investigators at this location control both the green key and the yellow key and spend 3 [per_investigator] clues, as a group: Take control of the purple key and read <b>Flashback IX</b> in the Campaign Guide.",
        "traits": "Cave. Y'ha-nthlei.",
        "type_code": "location"
    },
    {
        "back_flavor": "\"They had all kinds o' cities on the sea-bottom, an' this island was heaved up from thar.\"\n - H. P. Lovecraft, <u>The Shadow over Innsmouth</u>",
        "back_illustrator": "Frej Agelii",
        "back_name": "Unfathomable Depths",
        "clues": 1,
        "code": "07176a",
        "double_sided": true,
        "encounter_code": "devil_reef",
        "encounter_position": 16,
        "faction_code": "mythos",
        "illustrator": "Stanislav Dikolenko",
        "name": "Cyclopean Ruins",
        "pack_code": "def",
        "position": 176,
        "quantity": 1,
        "shroud": 3,
        "text": "<b>Forced</b> - After this location is revealed: It becomes fully flooded. Place the set-aside white key on it.\n[free] If investigators at this location control both the red key and the yellow key and spend 2 [per_investigator] clues, as a group: Take control of the white key and read <b>Flashback X</b> in the Campaign Guide.",
        "traits": "Cave. Y'ha-nthlei.",
        "type_code": "location"
    },
    {
        "back_flavor": "\"They had all kinds o' cities on the sea-bottom, an' this island was heaved up from thar.\" - H. P. Lovecraft, <u>The Shadow over Innsmouth</u>",
        "back_illustrator": "Frej Agelii",
        "back_name": "Unfathomable Depths",
        "clues": 2,
        "code": "07176b",
        "double_sided": true,
        "encounter_code": "devil_reef",
        "encounter_position": 17,
        "faction_code": "mythos",
        "illustrator": "Stanislav Dikolenko",
        "name": "Cyclopean Ruins",
        "pack_code": "def",
        "position": 176,
        "quantity": 1,
        "shroud": 1,
        "text": "<b>Forced</b> - After this location is revealed: It becomes fully flooded. Place the set-aside white key on it.\n[free] If investigators at this location control both the blue key and the green key and spend 3 [per_investigator] clues, as a group: Take control of the white key and read <b>Flashback X</b> in the Campaign Guide.",
        "traits": "Cave. Y'ha-nthlei.",
        "type_code": "location"
    },
    {
        "back_flavor": "\"They had all kinds o' cities on the sea-bottom, an' this island was heaved up from thar.\" - H. P. Lovecraft, <u>The Shadow over Innsmouth</u>",
        "back_illustrator": "Frej Agelii",
        "back_name": "Unfathomable Depths",
        "clues": 1,
        "code": "07177a",
        "double_sided": true,
        "encounter_code": "devil_reef",
        "encounter_position": 18,
        "faction_code": "mythos",
        "illustrator": "Vlad Ricean",
        "name": "Temple of the Union",
        "pack_code": "def",
        "position": 177,
        "quantity": 1,
        "shroud": 5,
        "text": "<b>Forced</b> - After this location is revealed: Place the set-aside black key on it.\n[free] If investigators at this location control both the red key and the green key and spend 2 [per_investigator] clues, as a group: Take control of the black key and read <b>Flashback XI</b> in the Campaign Guide.",
        "traits": "Cave. Y'ha-nthlei.",
        "type_code": "location"
    },
    {
        "back_flavor": "\"They had all kinds o' cities on the sea-bottom, an' this island was heaved up from thar.\" - H. P. Lovecraft, <u>The Shadow over Innsmouth</u>",
        "back_illustrator": "Frej Agelii",
        "back_name": "Unfathomable Depths",
        "clues": 2,
        "code": "07177b",
        "double_sided": true,
        "encounter_code": "devil_reef",
        "encounter_position": 19,
        "faction_code": "mythos",
        "illustrator": "Vlad Ricean",
        "name": "Temple of the Union",
        "pack_code": "def",
        "position": 177,
        "quantity": 1,
        "shroud": 3,
        "text": "<b>Forced</b> - After this location is revealed: Place the set-aside black key on it.\n[free] If investigators at this location control both the blue key and the yellow key and spend 3 [per_investigator] clues, as a group: Take control of the black key and read <b>Flashback XI</b> in the Campaign Guide.",
        "traits": "Cave. Y'ha-nthlei.",
        "type_code": "location"
    },
    {
        "code": "07178",
        "cost": null,
        "encounter_code": "devil_reef",
        "encounter_position": 20,
        "faction_code": "neutral",
        "illustrator": "Carlos Palma Cruchaga",
        "name": "Fishing Vessel",
        "pack_code": "def",
        "position": 178,
        "quantity": 1,
        "text": "Vehicle.\nWhile you are in this vehicle, treat your location as if it were unflooded.\n[action]: Move Fishing Vessel to a connecting [[Ocean]] location.",
        "traits": "Vehicle.",
        "type_code": "asset"
    },
    {
        "code": "07179",
        "cost": 1,
        "deck_limit": 1,
        "encounter_code": "devil_reef",
        "encounter_position": 21,
        "faction_code": "neutral",
        "illustrator": "Nino Vecia",
        "name": "Waveworn Idol",
        "pack_code": "def",
        "position": 179,
        "quantity": 1,
        "sanity": 2,
        "skill_intellect": 1,
        "skill_wild": 1,
        "text": "[reaction] After your location's flood level changes, or after a [[Deep One]] enemy spawns at your location, exhaust Waveworn Idol: Immediately take an action as if it were your turn (this action does not count toward the number of actions you can take each turn).",
        "traits": "Item. Relic.",
        "type_code": "asset"
    },
    {
        "code": "07180",
        "cost": 1,
        "deck_limit": 1,
        "encounter_code": "devil_reef",
        "encounter_position": 22,
        "faction_code": "neutral",
        "health": 2,
        "illustrator": "Nino Vecia",
        "name": "Awakened Mantle",
        "pack_code": "def",
        "position": 180,
        "quantity": 1,
        "skill_agility": 1,
        "skill_wild": 1,
        "text": "[free] If your location is flooded, exhaust Awakened Mantle: Move to a connecting location that is also flooded.",
        "traits": "Item. Relic. Clothing.",
        "type_code": "asset"
    },
    {
        "code": "07181",
        "cost": 1,
        "deck_limit": 1,
        "encounter_code": "devil_reef",
        "encounter_position": 23,
        "faction_code": "neutral",
        "health": 1,
        "illustrator": "Nino Vecia",
        "name": "Headdress of Y'ha-nthlei",
        "pack_code": "def",
        "position": 181,
        "quantity": 1,
        "sanity": 1,
        "skill_wild": 1,
        "skill_willpower": 1,
        "text": "You get +1 skill value while investigating a flooded location or while attacking or evading an enemy at a flooded location.",
        "traits": "Item. Relic.",
        "type_code": "asset"
    },
    {
        "code": "07182",
        "encounter_code": "devil_reef",
        "encounter_position": 24,
        "enemy_evade": 2,
        "enemy_fight": 4,
        "enemy_horror": 1,
        "faction_code": "mythos",
        "health": 2,
        "illustrator": "Dimitri Bielak",
        "name": "Deep One Predator",
        "pack_code": "def",
        "position": 182,
        "quantity": 2,
        "text": "Hunter.\n<b>Forced</b> - After Deep One Predator engages you: Move 1 of your clues or keys to Deep One Predator.\n<b>Forced</b> - When you defeat or evade Deep One Predator: Take control of all of its clues and keys.",
        "traits": "Humanoid. Monster. Deep One.",
        "type_code": "enemy"
    },
    {
        "code": "07183",
        "encounter_code": "devil_reef",
        "encounter_position": 26,
        "enemy_damage": 1,
        "enemy_evade": 3,
        "enemy_fight": 3,
        "enemy_horror": 1,
        "faction_code": "mythos",
        "health": 3,
        "illustrator": "Stephen Somers",
        "name": "Hunting Deep One",
        "pack_code": "def",
        "position": 183,
        "quantity": 2,
        "text": "Hunter.\nWhile Hunting Deep One is engaged with you, you cannot enter vehicles or gain resources.\n<b>Forced</b> - After Hunting Deep One engages you: If you are not in a vehicle, lose 2 resources. If you are in a vehicle, leave your vehicle.",
        "traits": "Humanoid. Monster. Deep One.",
        "type_code": "enemy"
    },
    {
        "code": "07184",
        "encounter_code": "devil_reef",
        "encounter_position": 28,
        "faction_code": "mythos",
        "flavor": "\"Did you see that?\"",
        "illustrator": "Raymond Bonilla",
        "name": "Shapes in the Water",
        "pack_code": "def",
        "position": 184,
        "quantity": 2,
        "text": "<b>Revelation</b> - Test [willpower] (2). If you fail, take 2 horror. This test gets +1 difficulty if your location is flooded (+2 difficulty instead if it is fully flooded).",
        "traits": "Terror.",
        "type_code": "treachery"
    },
    {
        "code": "07185",
        "encounter_code": "devil_reef",
        "encounter_position": 30,
        "faction_code": "mythos",
        "illustrator": "Franz Vohwinkel",
        "name": "Aquatic Ambush",
        "pack_code": "def",
        "position": 185,
        "quantity": 2,
        "text": "<b>Revelation</b> - Put Aquatic Ambush into play next to the agenda deck.\n<b>Forced</b> - When you reveal a chaos token while attacking an enemy at a flooded location: Reveal an additional chaos token. (Max once per test.)\n<b>Forced</b> - At the end of the round: Discard 1 copy of Aquatic Ambush from play. (Max once per round.)",
        "traits": "Scheme.",
        "type_code": "treachery"
    },
    {
        "code": "07186",
        "encounter_code": "devil_reef",
        "encounter_position": 32,
        "faction_code": "mythos",
        "illustrator": "Scott Purdy",
        "name": "Horrors from the Deep",
        "pack_code": "def",
        "position": 186,
        "quantity": 2,
        "text": "<b>Revelation</b> - Test [agility] (2). If you fail, take 2 damage. This test gets +1 difficulty if your location is flooded (+2 difficulty instead if it is fully flooded).",
        "traits": "Terror.",
        "type_code": "treachery"
    },
    {
        "code": "07187",
        "encounter_code": "devil_reef",
        "encounter_position": 34,
        "faction_code": "mythos",
        "illustrator": "Jacob Atienza",
        "name": "Stowaway",
        "pack_code": "def",
        "position": 187,
        "quantity": 2,
        "text": "<b>Revelation</b> - If no investigators are in a vehicle, Stowaway gains surge. Otherwise, each investigator in a vehicle must either take 1 damage and 1 horror or leave that vehicle. Each investigator who left a vehicle cannot enter that vehicle for the remainder of the round.",
        "traits": "Scheme.",
        "type_code": "treachery"
    },
    {
        "code": "07188",
        "encounter_code": "devil_reef",
        "encounter_position": 36,
        "faction_code": "mythos",
        "illustrator": "Régis Moulun",
        "name": "Dragged Under",
        "pack_code": "def",
        "position": 188,
        "quantity": 3,
        "text": "<b>Revelation</b> - Put Dragged Under into play in your threat area. If you are in a vehicle, leave it.\nYou cannot enter vehicles.\n[action]: Test [combat] (3) or [agility] (3). If you succeed, discard Dragged Under.",
        "traits": "Scheme. Terror.",
        "type_code": "treachery"
    }
]
